daisytuner/__init__.py
daisytuner/analysis/__init__.py
daisytuner/analysis/parallel_loop_nest.py
daisytuner/data/daisynet_v3.ckpt
daisytuner/data/nvidia_gpu_cc_ge_7/GPU_BRANCH.txt
daisytuner/data/nvidia_gpu_cc_ge_7/GPU_DRAM.txt
daisytuner/data/nvidia_gpu_cc_ge_7/GPU_FLOP_DP.txt
daisytuner/data/nvidia_gpu_cc_ge_7/GPU_FLOP_FP.txt
daisytuner/data/nvidia_gpu_cc_ge_7/GPU_FLOP_HP.txt
daisytuner/data/nvidia_gpu_cc_ge_7/GPU_GLD.txt
daisytuner/data/nvidia_gpu_cc_ge_7/GPU_INST1.txt
daisytuner/data/nvidia_gpu_cc_ge_7/GPU_INST10.txt
daisytuner/data/nvidia_gpu_cc_ge_7/GPU_INST11.txt
daisytuner/data/nvidia_gpu_cc_ge_7/GPU_INST12.txt
daisytuner/data/nvidia_gpu_cc_ge_7/GPU_INST2.txt
daisytuner/data/nvidia_gpu_cc_ge_7/GPU_INST3.txt
daisytuner/data/nvidia_gpu_cc_ge_7/GPU_INST4.txt
daisytuner/data/nvidia_gpu_cc_ge_7/GPU_INST5.txt
daisytuner/data/nvidia_gpu_cc_ge_7/GPU_INST6.txt
daisytuner/data/nvidia_gpu_cc_ge_7/GPU_INST7.txt
daisytuner/data/nvidia_gpu_cc_ge_7/GPU_INST8.txt
daisytuner/data/nvidia_gpu_cc_ge_7/GPU_INST9.txt
daisytuner/data/nvidia_gpu_cc_ge_7/GPU_L1TEX1.txt
daisytuner/data/nvidia_gpu_cc_ge_7/GPU_L1TEX10.txt
daisytuner/data/nvidia_gpu_cc_ge_7/GPU_L1TEX11.txt
daisytuner/data/nvidia_gpu_cc_ge_7/GPU_L1TEX2.txt
daisytuner/data/nvidia_gpu_cc_ge_7/GPU_L1TEX3.txt
daisytuner/data/nvidia_gpu_cc_ge_7/GPU_L1TEX4.txt
daisytuner/data/nvidia_gpu_cc_ge_7/GPU_L1TEX5.txt
daisytuner/data/nvidia_gpu_cc_ge_7/GPU_L1TEX6.txt
daisytuner/data/nvidia_gpu_cc_ge_7/GPU_L1TEX7.txt
daisytuner/data/nvidia_gpu_cc_ge_7/GPU_L1TEX8.txt
daisytuner/data/nvidia_gpu_cc_ge_7/GPU_L1TEX9.txt
daisytuner/data/nvidia_gpu_cc_ge_7/GPU_LOCAL1.txt
daisytuner/data/nvidia_gpu_cc_ge_7/GPU_LOCAL2.txt
daisytuner/data/nvidia_gpu_cc_ge_7/GPU_LOCAL4.txt
daisytuner/data/nvidia_gpu_cc_ge_7/GPU_LOCAL5.txt
daisytuner/data/nvidia_gpu_cc_ge_7/GPU_LTS1.txt
daisytuner/data/nvidia_gpu_cc_ge_7/GPU_LTS2.txt
daisytuner/data/nvidia_gpu_cc_ge_7/GPU_LTS3.txt
daisytuner/data/nvidia_gpu_cc_ge_7/GPU_MEM_SHARED1.txt
daisytuner-0.2.4.dist-info/LICENSE
daisytuner-0.2.4.dist-info/METADATA
daisytuner-0.2.4.dist-info/WHEEL
daisytuner-0.2.4.dist-info/top_level.txt
daisytuner-0.2.4.dist-info/RECORD
