Metadata-Version: 2.1
Name: daisytuner
Version: 0.2.4
Summary: A cloud-connected compiler pass for performance optimization
Home-page: https://daisytuner.com
Author: Lukas Truemper
Author-email: lukas.truemper@outlook.de
Classifier: Topic :: Utilities
Requires-Python: >=3.8
License-File: LICENSE
Requires-Dist: requests >=2.11.0
Requires-Dist: tqdm >=4.64.1
Requires-Dist: tabulate >=0.9.0
Requires-Dist: dace >=0.14.3
Requires-Dist: numpy >=1.23.0
Requires-Dist: pandas >=1.5.0
Requires-Dist: scikit-learn >=1.2.0
Requires-Dist: plotly >=5.11.0
Requires-Dist: seaborn >=0.2.12
Requires-Dist: kaleido >=0.2.1
Requires-Dist: opt-einsum >=3.3.0
Requires-Dist: torch >=1.13.0
Requires-Dist: torchvision
Requires-Dist: torchaudio
Requires-Dist: torchmetrics >=0.11.4
Requires-Dist: pytorch-lightning >=1.9.4
Requires-Dist: torch-geometric >=2.3
Requires-Dist: jupyterlab >=4.0.3
Provides-Extra: dev
Requires-Dist: black ==22.10.0 ; extra == 'dev'
Requires-Dist: pytest >=7.2.0 ; extra == 'dev'
Requires-Dist: pytest-cov >=4.1.0 ; extra == 'dev'
